<?xml version="1.0" ?>
<annotation>
<folder>JPEGImages</folder>
<filename>P0136.xml</filename>
<path>xxxx</path>
<source>
<database>Unknown</database>
<annotation>xxx</annotation>
<image>xxx</image>
<flickrid>0</flickrid>
</source>
<size>
<width>2904</width>
<height>2578</height>
<depth>3</depth>
</size>
<segmented>0</segmented>
<object>
<name>small-vehicle</name>
<bndbox>
<x1>2709</x1>
<y1>1813</y1>
<x2>2703</x2>
<y2>1827</y2>
<x3>2666</x3>
<y3>1815</y3>
<x4>2674</x4>
<y4>1797</y4>
</bndbox>
</object>
<object>
<name>small-vehicle</name>
<bndbox>
<x1>505</x1>
<y1>628</y1>
<x2>490</x2>
<y2>636</y2>
<x3>465</x3>
<y3>605</y3>
<x4>480</x4>
<y4>593</y4>
</bndbox>
</object>
<object>
<name>small-vehicle</name>
<bndbox>
<x1>290</x1>
<y1>317</y1>
<x2>309</x2>
<y2>317</y2>
<x3>307</x3>
<y3>356</y3>
<x4>288</x4>
<y4>355</y4>
</bndbox>
</object>
<object>
<name>small-vehicle</name>
<bndbox>
<x1>392</x1>
<y1>371</y1>
<x2>408</x2>
<y2>382</y2>
<x3>387</x3>
<y3>421</y3>
<x4>372</x4>
<y4>412</y4>
</bndbox>
</object>
<object>
<name>small-vehicle</name>
<bndbox>
<x1>338</x1>
<y1>435</y1>
<x2>357</x2>
<y2>432</y2>
<x3>363</x3>
<y3>469</y3>
<x4>345</x4>
<y4>472</y4>
</bndbox>
</object>
<object>
<name>small-vehicle</name>
<bndbox>
<x1>353</x1>
<y1>512</y1>
<x2>374</x2>
<y2>508</y2>
<x3>383</x3>
<y3>546</y3>
<x4>363</x4>
<y4>551</y4>
</bndbox>
</object>
<object>
<name>small-vehicle</name>
<bndbox>
<x1>365</x1>
<y1>559</y1>
<x2>384</x2>
<y2>555</y2>
<x3>394</x3>
<y3>592</y3>
<x4>375</x4>
<y4>594</y4>
</bndbox>
</object>
<object>
<name>small-vehicle</name>
<bndbox>
<x1>537</x1>
<y1>570</y1>
<x2>534</x2>
<y2>583</y2>
<x3>493</x3>
<y3>574</y3>
<x4>496</x4>
<y4>559</y4>
</bndbox>
</object>
<object>
<name>small-vehicle</name>
<bndbox>
<x1>396</x1>
<y1>674</y1>
<x2>415</x2>
<y2>671</y2>
<x3>426</x3>
<y3>711</y3>
<x4>406</x4>
<y4>716</y4>
</bndbox>
</object>
<object>
<name>small-vehicle</name>
<bndbox>
<x1>2798</x1>
<y1>1786</y1>
<x2>2840</x2>
<y2>1803</y2>
<x3>2836</x3>
<y3>1817</y3>
<x4>2792</x4>
<y4>1802</y4>
</bndbox>
</object>
<object>
<name>small-vehicle</name>
<bndbox>
<x1>408</x1>
<y1>724</y1>
<x2>426</x2>
<y2>720</y2>
<x3>436</x3>
<y3>758</y3>
<x4>417</x4>
<y4>763</y4>
</bndbox>
</object>
<object>
<name>small-vehicle</name>
<bndbox>
<x1>423</x1>
<y1>782</y1>
<x2>442</x2>
<y2>779</y2>
<x3>452</x3>
<y3>824</y3>
<x4>432</x4>
<y4>827</y4>
</bndbox>
</object>
<object>
<name>small-vehicle</name>
<bndbox>
<x1>456</x1>
<y1>981</y1>
<x2>477</x2>
<y2>980</y2>
<x3>485</x3>
<y3>1023</y3>
<x4>466</x4>
<y4>1025</y4>
</bndbox>
</object>
<object>
<name>small-vehicle</name>
<bndbox>
<x1>255</x1>
<y1>654</y1>
<x2>254</x2>
<y2>639</y2>
<x3>290</x3>
<y3>635</y3>
<x4>291</x4>
<y4>652</y4>
</bndbox>
</object>
<object>
<name>small-vehicle</name>
<bndbox>
<x1>184</x1>
<y1>671</y1>
<x2>181</x2>
<y2>657</y2>
<x3>218</x3>
<y3>652</y3>
<x4>220</x4>
<y4>665</y4>
</bndbox>
</object>
<object>
<name>roundabout</name>
<bndbox>
<x1>2059</x1>
<y1>1451</y1>
<x2>2500</x2>
<y2>1451</y2>
<x3>2500</x3>
<y3>1884</y3>
<x4>2059</x4>
<y4>1884</y4>
</bndbox>
</object>
<object>
<name>small-vehicle</name>
<bndbox>
<x1>679</x1>
<y1>1627</y1>
<x2>663</x2>
<y2>1634</y2>
<x3>648</x3>
<y3>1601</y3>
<x4>661</x4>
<y4>1593</y4>
</bndbox>
</object>
<object>
<name>small-vehicle</name>
<bndbox>
<x1>906</x1>
<y1>2393</y1>
<x2>918</x2>
<y2>2385</y2>
<x3>936</x3>
<y3>2414</y3>
<x4>924</x4>
<y4>2423</y4>
</bndbox>
</object>
<object>
<name>small-vehicle</name>
<bndbox>
<x1>774</x1>
<y1>2065</y1>
<x2>792</x2>
<y2>2059</y2>
<x3>811</x3>
<y3>2099</y3>
<x4>791</x4>
<y4>2107</y4>
</bndbox>
</object>
<object>
<name>small-vehicle</name>
<bndbox>
<x1>893</x1>
<y1>680</y1>
<x2>897</x2>
<y2>664</y2>
<x3>931</x3>
<y3>670</y3>
<x4>927</x4>
<y4>688</y4>
</bndbox>
</object>
<object>
<name>small-vehicle</name>
<bndbox>
<x1>937</x1>
<y1>688</y1>
<x2>940</x2>
<y2>672</y2>
<x3>982</x3>
<y3>682</y3>
<x4>979</x4>
<y4>701</y4>
</bndbox>
</object>
<object>
<name>small-vehicle</name>
<bndbox>
<x1>1058</x1>
<y1>745</y1>
<x2>1042</x2>
<y2>754</y2>
<x3>1020</x3>
<y3>724</y3>
<x4>1037</x4>
<y4>712</y4>
</bndbox>
</object>
<object>
<name>small-vehicle</name>
<bndbox>
<x1>1008</x1>
<y1>2522</y1>
<x2>993</x2>
<y2>2527</y2>
<x3>975</x3>
<y3>2509</y3>
<x4>991</x4>
<y4>2500</y4>
</bndbox>
</object>
<object>
<name>small-vehicle</name>
<bndbox>
<x1>1969</x1>
<y1>104</y1>
<x2>1954</x2>
<y2>114</y2>
<x3>1930</x3>
<y3>78</y3>
<x4>1948</x4>
<y4>69</y4>
</bndbox>
</object>
<object>
<name>small-vehicle</name>
<bndbox>
<x1>1855</x1>
<y1>174</y1>
<x2>1842</x2>
<y2>181</y2>
<x3>1825</x3>
<y3>156</y3>
<x4>1840</x4>
<y4>147</y4>
</bndbox>
</object>
<object>
<name>small-vehicle</name>
<bndbox>
<x1>2133</x1>
<y1>2392</y1>
<x2>2116</x2>
<y2>2388</y2>
<x3>2125</x3>
<y3>2355</y3>
<x4>2140</x4>
<y4>2358</y4>
</bndbox>
</object>
<object>
<name>small-vehicle</name>
<bndbox>
<x1>2165</x1>
<y1>2317</y1>
<x2>2178</x2>
<y2>2319</y2>
<x3>2171</x3>
<y3>2357</y3>
<x4>2155</x4>
<y4>2353</y4>
</bndbox>
</object>
<object>
<name>small-vehicle</name>
<bndbox>
<x1>2103</x1>
<y1>1431</y1>
<x2>2141</x2>
<y2>1404</y2>
<x3>2152</x3>
<y3>1420</y3>
<x4>2116</x4>
<y4>1447</y4>
</bndbox>
</object>
<object>
<name>small-vehicle</name>
<bndbox>
<x1>2460</x1>
<y1>2521</y1>
<x2>2456</x2>
<y2>2536</y2>
<x3>2419</x3>
<y3>2528</y3>
<x4>2423</x4>
<y4>2511</y4>
</bndbox>
</object>
<object>
<name>small-vehicle</name>
<bndbox>
<x1>2520</x1>
<y1>1852</y1>
<x2>2507</x2>
<y2>1842</y2>
<x3>2525</x3>
<y3>1812</y3>
<x4>2540</x4>
<y4>1822</y4>
</bndbox>
</object>
<object>
<name>small-vehicle</name>
<bndbox>
<x1>2559</x1>
<y1>1578</y1>
<x2>2576</x2>
<y2>1575</y2>
<x3>2579</x3>
<y3>1608</y3>
<x4>2562</x4>
<y4>1610</y4>
</bndbox>
</object>
<object>
<name>small-vehicle</name>
<bndbox>
<x1>2683</x1>
<y1>1742</y1>
<x2>2722</x2>
<y2>1758</y2>
<x3>2715</x3>
<y3>1773</y3>
<x4>2677</x4>
<y4>1758</y4>
</bndbox>
</object>
<object>
<name>small-vehicle</name>
<bndbox>
<x1>2738</x1>
<y1>1768</y1>
<x2>2769</x2>
<y2>1780</y2>
<x3>2764</x3>
<y3>1793</y3>
<x4>2734</x4>
<y4>1782</y4>
</bndbox>
</object>
<object>
<name>roundabout</name>
<bndbox>
<x1>557</x1>
<y1>1580</y1>
<x2>646</x2>
<y2>1580</y2>
<x3>646</x3>
<y3>1670</y3>
<x4>557</x4>
<y4>1670</y4>
</bndbox>
</object>
</annotation>