<?xml version="1.0" ?>
<annotation>
<folder>JPEGImages</folder>
<filename>P0458.xml</filename>
<path>xxxx</path>
<source>
<database>Unknown</database>
<annotation>xxx</annotation>
<image>xxx</image>
<flickrid>0</flickrid>
</source>
<size>
<width>1348</width>
<height>1155</height>
<depth>3</depth>
</size>
<segmented>0</segmented>
<object>
<name>small-vehicle</name>
<bndbox>
<x1>1100</x1>
<y1>589</y1>
<x2>1085</x2>
<y2>586</y2>
<x3>1094</x3>
<y3>550</y3>
<x4>1108</x4>
<y4>552</y4>
</bndbox>
</object>
<object>
<name>small-vehicle</name>
<bndbox>
<x1>1076</x1>
<y1>547</y1>
<x2>1092</x2>
<y2>550</y2>
<x3>1083</x3>
<y3>581</y3>
<x4>1069</x4>
<y4>578</y4>
</bndbox>
</object>
<object>
<name>small-vehicle</name>
<bndbox>
<x1>1052</x1>
<y1>522</y1>
<x2>1051</x2>
<y2>507</y2>
<x3>1080</x3>
<y3>504</y3>
<x4>1083</x4>
<y4>520</y4>
</bndbox>
</object>
<object>
<name>small-vehicle</name>
<bndbox>
<x1>676</x1>
<y1>209</y1>
<x2>663</x2>
<y2>223</y2>
<x3>634</x3>
<y3>190</y3>
<x4>648</x4>
<y4>177</y4>
</bndbox>
</object>
<object>
<name>small-vehicle</name>
<bndbox>
<x1>714</x1>
<y1>260</y1>
<x2>697</x2>
<y2>273</y2>
<x3>667</x3>
<y3>231</y3>
<x4>683</x4>
<y4>220</y4>
</bndbox>
</object>
<object>
<name>small-vehicle</name>
<bndbox>
<x1>303</x1>
<y1>675</y1>
<x2>308</x2>
<y2>659</y2>
<x3>342</x3>
<y3>672</y3>
<x4>337</x4>
<y4>687</y4>
</bndbox>
</object>
<object>
<name>swimming-pool</name>
<bndbox>
<x1>1165</x1>
<y1>697</y1>
<x2>1229</x2>
<y2>737</y2>
<x3>1213</x3>
<y3>762</y3>
<x4>1146</x4>
<y4>724</y4>
</bndbox>
</object>
<object>
<name>swimming-pool</name>
<bndbox>
<x1>960</x1>
<y1>577</y1>
<x2>1049</x2>
<y2>569</y2>
<x3>1057</x3>
<y3>611</y3>
<x4>967</x4>
<y4>617</y4>
</bndbox>
</object>
<object>
<name>swimming-pool</name>
<bndbox>
<x1>929</x1>
<y1>694</y1>
<x2>1000</x2>
<y2>727</y2>
<x3>978</x3>
<y3>772</y3>
<x4>906</x4>
<y4>739</y4>
</bndbox>
</object>
<object>
<name>swimming-pool</name>
<bndbox>
<x1>651</x1>
<y1>922</y1>
<x2>740</x2>
<y2>960</y2>
<x3>714</x3>
<y3>1018</y3>
<x4>627</x4>
<y4>975</y4>
</bndbox>
</object>
<object>
<name>swimming-pool</name>
<bndbox>
<x1>170</x1>
<y1>532</y1>
<x2>220</x2>
<y2>521</y2>
<x3>238</x3>
<y3>610</y3>
<x4>189</x4>
<y4>620</y4>
</bndbox>
</object>
<object>
<name>swimming-pool</name>
<bndbox>
<x1>334</x1>
<y1>255</y1>
<x2>370</x2>
<y2>278</y2>
<x3>325</x3>
<y3>355</y3>
<x4>288</x4>
<y4>336</y4>
</bndbox>
</object>
</annotation>