<?xml version="1.0" ?>
<annotation>
<folder>JPEGImages</folder>
<filename>P0538.xml</filename>
<path>xxxx</path>
<source>
<database>Unknown</database>
<annotation>xxx</annotation>
<image>xxx</image>
<flickrid>0</flickrid>
</source>
<size>
<width>2142</width>
<height>1124</height>
<depth>3</depth>
</size>
<segmented>0</segmented>
<object>
<name>ship</name>
<bndbox>
<x1>1425</x1>
<y1>806</y1>
<x2>1395</x2>
<y2>811</y2>
<x3>1378</x3>
<y3>722</y3>
<x4>1409</x4>
<y4>717</y4>
</bndbox>
</object>
<object>
<name>harbor</name>
<bndbox>
<x1>1582</x1>
<y1>352</y1>
<x2>1682</x2>
<y2>288</y2>
<x3>1871</x3>
<y3>573</y3>
<x4>1761</x4>
<y4>638</y4>
</bndbox>
</object>
<object>
<name>harbor</name>
<bndbox>
<x1>1485</x1>
<y1>660</y1>
<x2>1619</x2>
<y2>578</y2>
<x3>1746</x3>
<y3>799</y3>
<x4>1611</x4>
<y4>880</y4>
</bndbox>
</object>
<object>
<name>harbor</name>
<bndbox>
<x1>1406</x1>
<y1>717</y1>
<x2>1421</x2>
<y2>715</y2>
<x3>1462</x3>
<y3>944</y3>
<x4>1448</x4>
<y4>947</y4>
</bndbox>
</object>
<object>
<name>harbor</name>
<bndbox>
<x1>1213</x1>
<y1>620</y1>
<x2>1257</x2>
<y2>623</y2>
<x3>1237</x3>
<y3>928</y3>
<x4>1182</x4>
<y4>925</y4>
</bndbox>
</object>
<object>
<name>harbor</name>
<bndbox>
<x1>649</x1>
<y1>549</y1>
<x2>690</x2>
<y2>540</y2>
<x3>725</x3>
<y3>743</y3>
<x4>681</x4>
<y4>752</y4>
</bndbox>
</object>
<object>
<name>harbor</name>
<bndbox>
<x1>423</x1>
<y1>501</y1>
<x2>501</x2>
<y2>507</y2>
<x3>485</x3>
<y3>814</y3>
<x4>404</x4>
<y4>807</y4>
</bndbox>
</object>
<object>
<name>harbor</name>
<bndbox>
<x1>192</x1>
<y1>578</y1>
<x2>236</x2>
<y2>571</y2>
<x3>279</x3>
<y3>883</y3>
<x4>231</x4>
<y4>887</y4>
</bndbox>
</object>
</annotation>