<?xml version="1.0" ?>
<annotation>
<folder>JPEGImages</folder>
<filename>P0724.xml</filename>
<path>xxxx</path>
<source>
<database>Unknown</database>
<annotation>xxx</annotation>
<image>xxx</image>
<flickrid>0</flickrid>
</source>
<size>
<width>1658</width>
<height>1098</height>
<depth>3</depth>
</size>
<segmented>0</segmented>
<object>
<name>small-vehicle</name>
<bndbox>
<x1>702</x1>
<y1>766</y1>
<x2>708</x2>
<y2>754</y2>
<x3>735</x3>
<y3>769</y3>
<x4>729</x4>
<y4>781</y4>
</bndbox>
</object>
<object>
<name>small-vehicle</name>
<bndbox>
<x1>139</x1>
<y1>591</y1>
<x2>124</x2>
<y2>584</y2>
<x3>138</x3>
<y3>552</y3>
<x4>152</x4>
<y4>556</y4>
</bndbox>
</object>
<object>
<name>ship</name>
<bndbox>
<x1>579</x1>
<y1>174</y1>
<x2>611</x2>
<y2>197</y2>
<x3>544</x3>
<y3>300</y3>
<x4>514</x4>
<y4>276</y4>
</bndbox>
</object>
<object>
<name>ship</name>
<bndbox>
<x1>514</x1>
<y1>198</y1>
<x2>530</x2>
<y2>208</y2>
<x3>507</x3>
<y3>253</y3>
<x4>490</x4>
<y4>244</y4>
</bndbox>
</object>
<object>
<name>ship</name>
<bndbox>
<x1>463</x1>
<y1>243</y1>
<x2>439</x2>
<y2>223</y2>
<x3>492</x3>
<y3>148</y3>
<x4>517</x4>
<y4>165</y4>
</bndbox>
</object>
<object>
<name>ship</name>
<bndbox>
<x1>432</x1>
<y1>209</y1>
<x2>412</x2>
<y2>197</y2>
<x3>435</x3>
<y3>153</y3>
<x4>457</x4>
<y4>164</y4>
</bndbox>
</object>
<object>
<name>ship</name>
<bndbox>
<x1>380</x1>
<y1>231</y1>
<x2>345</x2>
<y2>208</y2>
<x3>401</x3>
<y3>104</y3>
<x4>439</x4>
<y4>126</y4>
</bndbox>
</object>
<object>
<name>ship</name>
<bndbox>
<x1>357</x1>
<y1>139</y1>
<x2>339</x2>
<y2>128</y2>
<x3>364</x3>
<y3>81</y3>
<x4>384</x4>
<y4>94</y4>
</bndbox>
</object>
<object>
<name>ship</name>
<bndbox>
<x1>236</x1>
<y1>1</y1>
<x2>279</x2>
<y2>2</y2>
<x3>223</x3>
<y3>92</y3>
<x4>190</x4>
<y4>73</y4>
</bndbox>
</object>
<object>
<name>ship</name>
<bndbox>
<x1>295</x1>
<y1>118</y1>
<x2>277</x2>
<y2>110</y2>
<x3>294</x3>
<y3>69</y3>
<x4>313</x4>
<y4>77</y4>
</bndbox>
</object>
<object>
<name>harbor</name>
<bndbox>
<x1>1381</x1>
<y1>688</y1>
<x2>1448</x2>
<y2>730</y2>
<x3>1356</x3>
<y3>884</y3>
<x4>1290</x4>
<y4>838</y4>
</bndbox>
</object>
<object>
<name>harbor</name>
<bndbox>
<x1>1476</x1>
<y1>742</y1>
<x2>1561</x2>
<y2>793</y2>
<x3>1464</x3>
<y3>955</y3>
<x4>1376</x4>
<y4>895</y4>
</bndbox>
</object>
<object>
<name>harbor</name>
<bndbox>
<x1>1256</x1>
<y1>614</y1>
<x2>1346</x2>
<y2>670</y2>
<x3>1259</x3>
<y3>820</y3>
<x4>1176</x4>
<y4>770</y4>
</bndbox>
</object>
<object>
<name>harbor</name>
<bndbox>
<x1>1087</x1>
<y1>510</y1>
<x2>1243</x2>
<y2>615</y2>
<x3>1148</x3>
<y3>760</y3>
<x4>1002</x4>
<y4>666</y4>
</bndbox>
</object>
<object>
<name>harbor</name>
<bndbox>
<x1>935</x1>
<y1>416</y1>
<x2>998</x2>
<y2>459</y2>
<x3>912</x3>
<y3>611</y3>
<x4>848</x4>
<y4>568</y4>
</bndbox>
</object>
<object>
<name>harbor</name>
<bndbox>
<x1>851</x1>
<y1>368</y1>
<x2>915</x2>
<y2>408</y2>
<x3>830</x3>
<y3>566</y3>
<x4>763</x4>
<y4>522</y4>
</bndbox>
</object>
<object>
<name>harbor</name>
<bndbox>
<x1>773</x1>
<y1>317</y1>
<x2>841</x2>
<y2>360</y2>
<x3>741</x3>
<y3>523</y3>
<x4>675</x4>
<y4>482</y4>
</bndbox>
</object>
<object>
<name>harbor</name>
<bndbox>
<x1>612</x1>
<y1>227</y1>
<x2>755</x2>
<y2>312</y2>
<x3>662</x3>
<y3>464</y3>
<x4>523</x4>
<y4>379</y4>
</bndbox>
</object>
<object>
<name>harbor</name>
<bndbox>
<x1>526</x1>
<y1>175</y1>
<x2>558</x2>
<y2>194</y2>
<x3>475</x3>
<y3>348</y3>
<x4>444</x4>
<y4>328</y4>
</bndbox>
</object>
<object>
<name>harbor</name>
<bndbox>
<x1>456</x1>
<y1>131</y1>
<x2>518</x2>
<y2>174</y2>
<x3>419</x3>
<y3>326</y3>
<x4>360</x4>
<y4>284</y4>
</bndbox>
</object>
<object>
<name>harbor</name>
<bndbox>
<x1>378</x1>
<y1>88</y1>
<x2>436</x2>
<y2>122</y2>
<x3>341</x3>
<y3>274</y3>
<x4>286</x4>
<y4>240</y4>
</bndbox>
</object>
<object>
<name>harbor</name>
<bndbox>
<x1>324</x1>
<y1>54</y1>
<x2>342</x2>
<y2>65</y2>
<x3>267</x3>
<y3>210</y3>
<x4>243</x4>
<y4>197</y4>
</bndbox>
</object>
<object>
<name>harbor</name>
<bndbox>
<x1>211</x1>
<y1>0</y1>
<x2>295</x2>
<y2>3</y2>
<x3>195</x3>
<y3>168</y3>
<x4>130</x4>
<y4>126</y4>
</bndbox>
</object>
<object>
<name>ship</name>
<bndbox>
<x1>682</x1>
<y1>259</y1>
<x2>710</x2>
<y2>278</y2>
<x3>647</x3>
<y3>373</y3>
<x4>620</x4>
<y4>354</y4>
</bndbox>
</object>
<object>
<name>ship</name>
<bndbox>
<x1>692</x1>
<y1>394</y1>
<x2>660</x2>
<y2>373</y2>
<x3>720</x3>
<y3>272</y3>
<x4>757</x4>
<y4>296</y4>
</bndbox>
</object>
<object>
<name>ship</name>
<bndbox>
<x1>791</x1>
<y1>282</y1>
<x2>830</x2>
<y2>307</y2>
<x3>748</x3>
<y3>428</y3>
<x4>713</x4>
<y4>402</y4>
</bndbox>
</object>
<object>
<name>small-vehicle</name>
<bndbox>
<x1>109</x1>
<y1>466</y1>
<x2>100</x2>
<y2>481</y2>
<x3>67</x3>
<y3>464</y3>
<x4>75</x4>
<y4>448</y4>
</bndbox>
</object>
<object>
<name>small-vehicle</name>
<bndbox>
<x1>997</x1>
<y1>1080</y1>
<x2>982</x2>
<y2>1089</y2>
<x3>962</x3>
<y3>1060</y3>
<x4>978</x4>
<y4>1050</y4>
</bndbox>
</object>
<object>
<name>small-vehicle</name>
<bndbox>
<x1>872</x1>
<y1>953</y1>
<x2>884</x2>
<y2>944</y2>
<x3>910</x3>
<y3>971</y3>
<x4>897</x4>
<y4>981</y4>
</bndbox>
</object>
<object>
<name>small-vehicle</name>
<bndbox>
<x1>52</x1>
<y1>781</y1>
<x2>33</x2>
<y2>772</y2>
<x3>53</x3>
<y3>728</y3>
<x4>72</x4>
<y4>736</y4>
</bndbox>
</object>
<object>
<name>small-vehicle</name>
<bndbox>
<x1>110</x1>
<y1>746</y1>
<x2>92</x2>
<y2>739</y2>
<x3>108</x3>
<y3>701</y3>
<x4>126</x4>
<y4>708</y4>
</bndbox>
</object>
<object>
<name>small-vehicle</name>
<bndbox>
<x1>128</x1>
<y1>705</y1>
<x2>107</x2>
<y2>694</y2>
<x3>127</x3>
<y3>658</y3>
<x4>146</x4>
<y4>667</y4>
</bndbox>
</object>
<object>
<name>small-vehicle</name>
<bndbox>
<x1>298</x1>
<y1>578</y1>
<x2>288</x2>
<y2>596</y2>
<x3>257</x3>
<y3>579</y3>
<x4>266</x4>
<y4>562</y4>
</bndbox>
</object>
<object>
<name>small-vehicle</name>
<bndbox>
<x1>189</x1>
<y1>562</y1>
<x2>170</x2>
<y2>563</y2>
<x3>171</x3>
<y3>524</y3>
<x4>191</x4>
<y4>523</y4>
</bndbox>
</object>
<object>
<name>small-vehicle</name>
<bndbox>
<x1>869</x1>
<y1>868</y1>
<x2>879</x2>
<y2>852</y2>
<x3>912</x3>
<y3>875</y3>
<x4>903</x4>
<y4>890</y4>
</bndbox>
</object>
<object>
<name>small-vehicle</name>
<bndbox>
<x1>785</x1>
<y1>819</y1>
<x2>794</x2>
<y2>804</y2>
<x3>830</x3>
<y3>826</y3>
<x4>821</x4>
<y4>840</y4>
</bndbox>
</object>
<object>
<name>small-vehicle</name>
<bndbox>
<x1>662</x1>
<y1>724</y1>
<x2>656</x2>
<y2>739</y2>
<x3>629</x3>
<y3>724</y3>
<x4>636</x4>
<y4>708</y4>
</bndbox>
</object>
<object>
<name>ship</name>
<bndbox>
<x1>806</x1>
<y1>406</y1>
<x2>791</x2>
<y2>396</y2>
<x3>815</x3>
<y3>354</y3>
<x4>832</x4>
<y4>364</y4>
</bndbox>
</object>
<object>
<name>small-vehicle</name>
<bndbox>
<x1>489</x1>
<y1>701</y1>
<x2>479</x2>
<y2>716</y2>
<x3>445</x3>
<y3>691</y3>
<x4>457</x4>
<y4>675</y4>
</bndbox>
</object>
<object>
<name>small-vehicle</name>
<bndbox>
<x1>372</x1>
<y1>573</y1>
<x2>382</x2>
<y2>556</y2>
<x3>419</x3>
<y3>579</y3>
<x4>409</x4>
<y4>596</y4>
</bndbox>
</object>
<object>
<name>ship</name>
<bndbox>
<x1>1491</x1>
<y1>866</y1>
<x2>1472</x2>
<y2>856</y2>
<x3>1496</x3>
<y3>807</y3>
<x4>1516</x4>
<y4>818</y4>
</bndbox>
</object>
<object>
<name>ship</name>
<bndbox>
<x1>1260</x1>
<y1>781</y1>
<x2>1225</x2>
<y2>760</y2>
<x3>1293</x3>
<y3>629</y3>
<x4>1332</x4>
<y4>649</y4>
</bndbox>
</object>
<object>
<name>ship</name>
<bndbox>
<x1>1219</x1>
<y1>704</y1>
<x2>1202</x2>
<y2>689</y2>
<x3>1232</x3>
<y3>648</y3>
<x4>1250</x4>
<y4>663</y4>
</bndbox>
</object>
<object>
<name>ship</name>
<bndbox>
<x1>951</x1>
<y1>576</y1>
<x2>932</x2>
<y2>562</y2>
<x3>960</x3>
<y3>515</y3>
<x4>978</x4>
<y4>529</y4>
</bndbox>
</object>
<object>
<name>ship</name>
<bndbox>
<x1>984</x1>
<y1>514</y1>
<x2>968</x2>
<y2>503</y2>
<x3>992</x3>
<y3>460</y3>
<x4>1010</x4>
<y4>469</y4>
</bndbox>
</object>
<object>
<name>ship</name>
<bndbox>
<x1>918</x1>
<y1>522</y1>
<x2>899</x2>
<y2>509</y2>
<x3>927</x3>
<y3>462</y3>
<x4>946</x4>
<y4>475</y4>
</bndbox>
</object>
<object>
<name>ship</name>
<bndbox>
<x1>890</x1>
<y1>384</y1>
<x2>922</x2>
<y2>400</y2>
<x3>862</x3>
<y3>508</y3>
<x4>830</x4>
<y4>489</y4>
</bndbox>
</object>
<object>
<name>harbor</name>
<bndbox>
<x1>104</x1>
<y1>0</y1>
<x2>182</x2>
<y2>2</y2>
<x3>108</x3>
<y3>125</y3>
<x4>44</x4>
<y4>89</y4>
</bndbox>
</object>
</annotation>