<?xml version="1.0" ?>
<annotation>
<folder>JPEGImages</folder>
<filename>P0754.xml</filename>
<path>xxxx</path>
<source>
<database>Unknown</database>
<annotation>xxx</annotation>
<image>xxx</image>
<flickrid>0</flickrid>
</source>
<size>
<width>915</width>
<height>1159</height>
<depth>3</depth>
</size>
<segmented>0</segmented>
<object>
<name>small-vehicle</name>
<bndbox>
<x1>581</x1>
<y1>502</y1>
<x2>593</x2>
<y2>487</y2>
<x3>624</x3>
<y3>512</y3>
<x4>612</x4>
<y4>527</y4>
</bndbox>
</object>
<object>
<name>small-vehicle</name>
<bndbox>
<x1>594</x1>
<y1>488</y1>
<x2>607</x2>
<y2>470</y2>
<x3>640</x3>
<y3>491</y3>
<x4>627</x4>
<y4>510</y4>
</bndbox>
</object>
<object>
<name>large-vehicle</name>
<bndbox>
<x1>751</x1>
<y1>166</y1>
<x2>741</x2>
<y2>181</y2>
<x3>676</x3>
<y3>132</y3>
<x4>687</x4>
<y4>117</y4>
</bndbox>
</object>
<object>
<name>large-vehicle</name>
<bndbox>
<x1>386</x1>
<y1>790</y1>
<x2>370</x2>
<y2>780</y2>
<x3>441</x3>
<y3>661</y3>
<x4>459</x4>
<y4>672</y4>
</bndbox>
</object>
<object>
<name>large-vehicle</name>
<bndbox>
<x1>346</x1>
<y1>674</y1>
<x2>334</x2>
<y2>688</y2>
<x3>270</x3>
<y3>636</y3>
<x4>282</x4>
<y4>621</y4>
</bndbox>
</object>
<object>
<name>large-vehicle</name>
<bndbox>
<x1>316</x1>
<y1>682</y1>
<x2>306</x2>
<y2>698</y2>
<x3>254</x3>
<y3>659</y3>
<x4>265</x4>
<y4>643</y4>
</bndbox>
</object>
<object>
<name>large-vehicle</name>
<bndbox>
<x1>288</x1>
<y1>701</y1>
<x2>277</x2>
<y2>713</y2>
<x3>233</x3>
<y3>683</y3>
<x4>247</x4>
<y4>666</y4>
</bndbox>
</object>
<object>
<name>large-vehicle</name>
<bndbox>
<x1>277</x1>
<y1>727</y1>
<x2>266</x2>
<y2>743</y2>
<x3>216</x3>
<y3>705</y3>
<x4>227</x4>
<y4>690</y4>
</bndbox>
</object>
<object>
<name>large-vehicle</name>
<bndbox>
<x1>243</x1>
<y1>748</y1>
<x2>234</x2>
<y2>760</y2>
<x3>195</x3>
<y3>729</y3>
<x4>205</x4>
<y4>717</y4>
</bndbox>
</object>
<object>
<name>large-vehicle</name>
<bndbox>
<x1>208</x1>
<y1>794</y1>
<x2>196</x2>
<y2>810</y2>
<x3>156</x3>
<y3>779</y3>
<x4>167</x4>
<y4>763</y4>
</bndbox>
</object>
<object>
<name>small-vehicle</name>
<bndbox>
<x1>614</x1>
<y1>233</y1>
<x2>626</x2>
<y2>216</y2>
<x3>655</x3>
<y3>238</y3>
<x4>644</x4>
<y4>255</y4>
</bndbox>
</object>
<object>
<name>small-vehicle</name>
<bndbox>
<x1>627</x1>
<y1>213</y1>
<x2>638</x2>
<y2>197</y2>
<x3>669</x3>
<y3>224</y3>
<x4>662</x4>
<y4>238</y4>
</bndbox>
</object>
<object>
<name>small-vehicle</name>
<bndbox>
<x1>558</x1>
<y1>335</y1>
<x2>544</x2>
<y2>351</y2>
<x3>510</x3>
<y3>325</y3>
<x4>525</x4>
<y4>304</y4>
</bndbox>
</object>
<object>
<name>small-vehicle</name>
<bndbox>
<x1>47</x1>
<y1>942</y1>
<x2>59</x2>
<y2>925</y2>
<x3>92</x3>
<y3>951</y3>
<x4>79</x4>
<y4>965</y4>
</bndbox>
</object>
<object>
<name>small-vehicle</name>
<bndbox>
<x1>73</x1>
<y1>963</y1>
<x2>61</x2>
<y2>978</y2>
<x3>31</x3>
<y3>954</y3>
<x4>44</x4>
<y4>937</y4>
</bndbox>
</object>
<object>
<name>small-vehicle</name>
<bndbox>
<x1>23</x1>
<y1>971</y1>
<x2>34</x2>
<y2>957</y2>
<x3>60</x3>
<y3>979</y3>
<x4>48</x4>
<y4>992</y4>
</bndbox>
</object>
<object>
<name>small-vehicle</name>
<bndbox>
<x1>8</x1>
<y1>987</y1>
<x2>18</x2>
<y2>973</y2>
<x3>45</x3>
<y3>997</y3>
<x4>34</x4>
<y4>1010</y4>
</bndbox>
</object>
<object>
<name>small-vehicle</name>
<bndbox>
<x1>185</x1>
<y1>1123</y1>
<x2>178</x2>
<y2>1138</y2>
<x3>146</x3>
<y3>1119</y3>
<x4>154</x4>
<y4>1104</y4>
</bndbox>
</object>
<object>
<name>small-vehicle</name>
<bndbox>
<x1>196</x1>
<y1>1104</y1>
<x2>187</x2>
<y2>1120</y2>
<x3>155</x3>
<y3>1100</y3>
<x4>162</x4>
<y4>1084</y4>
</bndbox>
</object>
<object>
<name>large-vehicle</name>
<bndbox>
<x1>67</x1>
<y1>1047</y1>
<x2>84</x2>
<y2>1058</y2>
<x3>43</x3>
<y3>1123</y3>
<x4>23</x4>
<y4>1112</y4>
</bndbox>
</object>
<object>
<name>large-vehicle</name>
<bndbox>
<x1>521</x1>
<y1>458</y1>
<x2>509</x2>
<y2>476</y2>
<x3>445</x3>
<y3>424</y3>
<x4>456</x4>
<y4>407</y4>
</bndbox>
</object>
<object>
<name>large-vehicle</name>
<bndbox>
<x1>520</x1>
<y1>411</y1>
<x2>510</x2>
<y2>430</y2>
<x3>460</x3>
<y3>397</y3>
<x4>474</x4>
<y4>378</y4>
</bndbox>
</object>
<object>
<name>small-vehicle</name>
<bndbox>
<x1>870</x1>
<y1>148</y1>
<x2>871</x2>
<y2>131</y2>
<x3>911</x3>
<y3>136</y3>
<x4>911</x4>
<y4>151</y4>
</bndbox>
</object>
<object>
<name>small-vehicle</name>
<bndbox>
<x1>877</x1>
<y1>124</y1>
<x2>877</x2>
<y2>107</y2>
<x3>911</x3>
<y3>109</y3>
<x4>910</x4>
<y4>126</y4>
</bndbox>
</object>
<object>
<name>small-vehicle</name>
<bndbox>
<x1>720</x1>
<y1>323</y1>
<x2>734</x2>
<y2>305</y2>
<x3>768</x3>
<y3>331</y3>
<x4>756</x4>
<y4>348</y4>
</bndbox>
</object>
<object>
<name>small-vehicle</name>
<bndbox>
<x1>711</x1>
<y1>342</y1>
<x2>722</x2>
<y2>325</y2>
<x3>754</x3>
<y3>349</y3>
<x4>744</x4>
<y4>363</y4>
</bndbox>
</object>
<object>
<name>small-vehicle</name>
<bndbox>
<x1>688</x1>
<y1>373</y1>
<x2>699</x2>
<y2>354</y2>
<x3>737</x3>
<y3>379</y3>
<x4>726</x4>
<y4>397</y4>
</bndbox>
</object>
<object>
<name>small-vehicle</name>
<bndbox>
<x1>666</x1>
<y1>402</y1>
<x2>675</x2>
<y2>388</y2>
<x3>706</x3>
<y3>409</y3>
<x4>697</x4>
<y4>424</y4>
</bndbox>
</object>
<object>
<name>small-vehicle</name>
<bndbox>
<x1>646</x1>
<y1>415</y1>
<x2>655</x2>
<y2>401</y2>
<x3>690</x3>
<y3>423</y3>
<x4>680</x4>
<y4>436</y4>
</bndbox>
</object>
<object>
<name>large-vehicle</name>
<bndbox>
<x1>766</x1>
<y1>142</y1>
<x2>756</x2>
<y2>154</y2>
<x3>694</x3>
<y3>108</y3>
<x4>707</x4>
<y4>92</y4>
</bndbox>
</object>
</annotation>